{
    "key": "group_64f3d19c333a8",
    "title": "Home Page Hero",
    "fields": [
        {
            "key": "field_64f3d8154f7f2",
            "label": "Hero Image",
            "name": "hero_image",
            "aria-label": "",
            "type": "image",
            "instructions": "",
            "required": 0,
            "conditional_logic": 0,
            "wrapper": {
                "width": "",
                "class": "",
                "id": ""
            },
            "return_format": "id",
            "library": "all",
            "min_width": "",
            "min_height": "",
            "min_size": "",
            "max_width": "",
            "max_height": "",
            "max_size": "",
            "mime_types": "",
            "preview_size": "medium"
        },
        {
            "key": "field_64f3d1ea659d9",
            "label": "Hero Preheading",
            "name": "hero_preheading",
            "aria-label": "",
            "type": "text",
            "instructions": "",
            "required": 0,
            "conditional_logic": 0,
            "wrapper": {
                "width": "",
                "class": "",
                "id": ""
            },
            "default_value": "A Insert Location Here Gym",
            "maxlength": "",
            "placeholder": "",
            "prepend": "",
            "append": ""
        },
        {
            "key": "field_64f3d19c659d7",
            "label": "Hero Heading",
            "name": "hero_heading",
            "aria-label": "",
            "type": "text",
            "instructions": "",
            "required": 0,
            "conditional_logic": 0,
            "wrapper": {
                "width": "",
                "class": "",
                "id": ""
            },
            "default_value": "Welcome To Our Gym",
            "maxlength": "",
            "placeholder": "",
            "prepend": "",
            "append": ""
        },
        {
            "key": "field_64f3d1bb659d8",
            "label": "Hero Content",
            "name": "hero_content",
            "aria-label": "",
            "type": "textarea",
            "instructions": "",
            "required": 0,
            "conditional_logic": 0,
            "wrapper": {
                "width": "",
                "class": "",
                "id": ""
            },
            "default_value": "",
            "maxlength": "",
            "rows": "",
            "placeholder": "",
            "new_lines": ""
        },
        {
            "key": "field_64f3d214659da",
            "label": "Hero Button Text",
            "name": "hero_button_text",
            "aria-label": "",
            "type": "text",
            "instructions": "",
            "required": 0,
            "conditional_logic": 0,
            "wrapper": {
                "width": "",
                "class": "",
                "id": ""
            },
            "default_value": "Learn More",
            "maxlength": "",
            "placeholder": "",
            "prepend": "",
            "append": ""
        },
        {
            "key": "field_64f3d229659db",
            "label": "Hero Button URL",
            "name": "hero_button_url",
            "aria-label": "",
            "type": "url",
            "instructions": "",
            "required": 0,
            "conditional_logic": 0,
            "wrapper": {
                "width": "",
                "class": "",
                "id": ""
            },
            "default_value": "https:\/\/google.com",
            "placeholder": ""
        },
        {
            "key": "field_64f61bc6bfe9c",
            "label": "Home Secondary Button",
            "name": "home_secondary_button",
            "aria-label": "",
            "type": "true_false",
            "instructions": "",
            "required": 0,
            "conditional_logic": 0,
            "wrapper": {
                "width": "",
                "class": "",
                "id": ""
            },
            "message": "Do you want to display a secondary call to action button?",
            "default_value": 0,
            "ui": 0,
            "ui_on_text": "",
            "ui_off_text": ""
        },
        {
            "key": "field_64f3d257659dc",
            "label": "Hero Button 2 Text",
            "name": "hero_button_2_text",
            "aria-label": "",
            "type": "text",
            "instructions": "",
            "required": 0,
            "conditional_logic": [
                [
                    {
                        "field": "field_64f61bc6bfe9c",
                        "operator": "==",
                        "value": "1"
                    }
                ]
            ],
            "wrapper": {
                "width": "",
                "class": "",
                "id": ""
            },
            "default_value": "Do something else",
            "maxlength": "",
            "placeholder": "",
            "prepend": "",
            "append": ""
        },
        {
            "key": "field_64f3d265659dd",
            "label": "Hero Button 2 URL",
            "name": "hero_button_2_url",
            "aria-label": "",
            "type": "url",
            "instructions": "",
            "required": 0,
            "conditional_logic": [
                [
                    {
                        "field": "field_64f61bc6bfe9c",
                        "operator": "==",
                        "value": "1"
                    }
                ]
            ],
            "wrapper": {
                "width": "",
                "class": "",
                "id": ""
            },
            "default_value": "https:\/\/apple.com",
            "placeholder": ""
        }
    ],
    "location": [
        [
            {
                "param": "page_type",
                "operator": "==",
                "value": "front_page"
            }
        ]
    ],
    "menu_order": 0,
    "position": "normal",
    "style": "default",
    "label_placement": "top",
    "instruction_placement": "label",
    "hide_on_screen": [
        "the_content"
    ],
    "active": true,
    "description": "",
    "show_in_rest": 0,
    "modified": 1695069559
}
